solc_ast_parser/__init__.py
solc_ast_parser/comments.py
solc_ast_parser/enrichment.py
solc_ast_parser/utils.py
solc_ast_parser/models/__init__.py
solc_ast_parser/models/ast_models.py
solc_ast_parser/models/base_ast_models.py
solc_ast_parser/models/yul_models.py
solc_ast_parser-1.4.5.dist-info/licenses/LICENSE
solc_ast_parser-1.4.5.dist-info/METADATA
solc_ast_parser-1.4.5.dist-info/WHEEL
solc_ast_parser-1.4.5.dist-info/top_level.txt
solc_ast_parser-1.4.5.dist-info/RECORD
